sqliteview/Controller.py
sqliteview/__init__.py
sqliteview/__main__.py
sqliteview/model/Database.py
sqliteview/model/Table.py
sqliteview/model/__init__.py
sqliteview/sqlite/Command.py
sqliteview/sqlite/__init__.py
sqliteview-1.0.1.dist-info/LICENSE.md
sqliteview-1.0.1.dist-info/METADATA
sqliteview-1.0.1.dist-info/WHEEL
sqliteview-1.0.1.dist-info/entry_points.txt
sqliteview-1.0.1.dist-info/top_level.txt
sqliteview-1.0.1.dist-info/RECORD
